dimensionality_reduction/__init__.py
dimensionality_reduction/dimensionality_reduction.py
dimensionality_reduction/services/__init__.py
dimensionality_reduction/services/plot_service.py
dimensionality_reduction_package-1.0.0.dist-info/LICENSE
dimensionality_reduction_package-1.0.0.dist-info/METADATA
dimensionality_reduction_package-1.0.0.dist-info/WHEEL
dimensionality_reduction_package-1.0.0.dist-info/top_level.txt
dimensionality_reduction_package-1.0.0.dist-info/RECORD
