Metadata-Version: 2.1
Name: dimensionality-reduction-package
Version: 1.0.0
Home-page: https://github.com/matteo-serafino/dimensionality-reduction-package
Author: Matteo Serafino
Author-email: matteo.serafino1@gmail.com
License: MIT
Keywords: dimensionality reduction
Requires-Python: >=3.6.2
License-File: LICENSE
Requires-Dist: colorama (>=0.4.5)
Requires-Dist: cycler (>=0.11.0)
Requires-Dist: fonttools (>=4.33.3)
Requires-Dist: joblib (>=1.1.0)
Requires-Dist: kiwisolver (>=1.4.3)
Requires-Dist: llvmlite (>=0.38.1)
Requires-Dist: matplotlib (>=3.5.2)
Requires-Dist: numba (>=0.55.2)
Requires-Dist: numpy (>=1.22.4)
Requires-Dist: packaging (>=21.3)
Requires-Dist: pandas (>=1.4.2)
Requires-Dist: Pillow (>=9.1.1)
Requires-Dist: pynndescent (>=0.5.7)
Requires-Dist: pyparsing (>=3.0.9)
Requires-Dist: python-dateutil (>=2.8.2)
Requires-Dist: pytz (>=2022.1)
Requires-Dist: scikit-learn (>=1.1.1)
Requires-Dist: scipy (>=1.8.1)
Requires-Dist: seaborn (>=0.11.2)
Requires-Dist: six (>=1.16.0)
Requires-Dist: threadpoolctl (>=3.1.0)
Requires-Dist: tqdm (>=4.64.0)
Requires-Dist: umap-learn (>=0.5.3)
